dhkit
