Metadata-Version: 1.0
Name: dhkit
Version: 1.0.22
Summary: smallpay python toolkit
Home-page: https://gitlab.com/smallpay/dhkit
Author: tufei
Author-email: tufei@infohold.com.cn
License: UNKNOWN
Platform: UNKNOWN
